{
  "OωO": {
    "type": "emoticon",
    "container": [
      { "icon": "OωO", "text": "Author: DIYgod" },
      { "icon": "|´・ω・)ノ", "text": "Hi" },
      { "icon": "ヾ(≧∇≦*)ゝ", "text": "开心" },
      { "icon": "(☆ω☆)", "text": "星星眼" },
      { "icon": "（╯‵□′）╯︵┴─┴", "text": "掀桌" },
      { "icon": "￣﹃￣", "text": "流口水" },
      { "icon": "(/ω＼)", "text": "捂脸" },
      { "icon": "∠( ᐛ 」∠)＿", "text": "给跪" },
      { "icon": "(๑•̀ㅁ•́ฅ)", "text": "Hi" },
      { "icon": "→_→", "text": "斜眼" },
      { "icon": "୧(๑•̀⌄•́๑)૭", "text": "加油" },
      { "icon": "٩(ˊᗜˋ*)و", "text": "有木有WiFi" },
      { "icon": "(ノ°ο°)ノ", "text": "前方高能预警" },
      { "icon": "(´இ皿இ｀)", "text": "我从未见过如此厚颜无耻之人" },
      { "icon": "⌇●﹏●⌇", "text": "吓死宝宝惹" },
      { "icon": "(ฅ´ω`ฅ)", "text": "已阅留爪" },
      { "icon": "(╯°A°)╯︵○○○", "text": "去吧大师球" },
      { "icon": "φ(￣∇￣o)", "text": "太萌惹" },
      { "icon": "ヾ(´･ ･｀｡)ノ\"", "text": "咦咦咦" },
      { "icon": "( ง ᵒ̌皿ᵒ̌)ง⁼³₌₃", "text": "气呼呼" },
      { "icon": "(ó﹏ò｡)", "text": "我受到了惊吓" },
      { "icon": "Σ(っ °Д °;)っ", "text": "什么鬼" },
      { "icon": "( ,,´･ω･)ﾉ\"(´っω･｀｡)", "text": "摸摸头" },
      { "icon": "╮(╯▽╰)╭ ", "text": "无奈" },
      { "icon": "o(*////▽////*)q ", "text": "脸红" },
      { "icon": "＞﹏＜", "text": "" },
      { "icon": "( ๑´•ω•) \"(ㆆᴗㆆ)", "text": "" }
    ]
  },
  "2233娘":{
    "type":"image",
    "container":[
      {
        "text":"bilibili2233-1",
        "icon":"<img src='https://cdn.jsdelivr.net/gh/2x-ercha/twikoo-magic@master/image/bilibili2233/[2233娘_卖萌].png'>"
      },
      {
        "text":"bilibili2233-2",
        "icon":"<img src='https://cdn.jsdelivr.net/gh/2x-ercha/twikoo-magic@master/image/bilibili2233/[2233娘_吃惊].png'>"
      },
      {
        "text":"bilibili2233-3",
        "icon":"<img src='https://cdn.jsdelivr.net/gh/2x-ercha/twikoo-magic@master/image/bilibili2233/[2233娘_吐魂].png'>"
      },
      {
        "text":"bilibili2233-4",
        "icon":"<img src='https://cdn.jsdelivr.net/gh/2x-ercha/twikoo-magic@master/image/bilibili2233/[2233娘_喝水].png'>"
      },
      {
        "text":"bilibili2233-5",
        "icon":"<img src='https://cdn.jsdelivr.net/gh/2x-ercha/twikoo-magic@master/image/bilibili2233/[2233娘_困惑].png'>"
      },
      {
        "text":"bilibili2233-6",
        "icon":"<img src='https://cdn.jsdelivr.net/gh/2x-ercha/twikoo-magic@master/image/bilibili2233/[2233娘_大哭].png'>"
      },
      {
        "text":"bilibili2233-7",
        "icon":"<img src='https://cdn.jsdelivr.net/gh/2x-ercha/twikoo-magic@master/image/bilibili2233/[2233娘_大笑].png'>"
      },
      {
        "text":"bilibili2233-8",
        "icon":"<img src='https://cdn.jsdelivr.net/gh/2x-ercha/twikoo-magic@master/image/bilibili2233/[2233娘_委屈].png'>"
      },
      {
        "text":"bilibili2233-9",
        "icon":"<img src='https://cdn.jsdelivr.net/gh/2x-ercha/twikoo-magic@master/image/bilibili2233/[2233娘_怒].png'>"
      },
      {
        "text":"bilibili2233-10",
        "icon":"<img src='https://cdn.jsdelivr.net/gh/2x-ercha/twikoo-magic@master/image/bilibili2233/[2233娘_无言].png'>"
      },
      {
        "text":"bilibili2233-11",
        "icon":"<img src='https://cdn.jsdelivr.net/gh/2x-ercha/twikoo-magic@master/image/bilibili2233/[2233娘_汗].png'>"
      },
      {
        "text":"bilibili2233-12",
        "icon":"<img src='https://cdn.jsdelivr.net/gh/2x-ercha/twikoo-magic@master/image/bilibili2233/[2233娘_疑问].png'>"
      },
      {
        "text":"bilibili2233-13",
        "icon":"<img src='https://cdn.jsdelivr.net/gh/2x-ercha/twikoo-magic@master/image/bilibili2233/[2233娘_第一].png'>"
      },
      {
        "text":"bilibili2233-14",
        "icon":"<img src='https://cdn.jsdelivr.net/gh/2x-ercha/twikoo-magic@master/image/bilibili2233/[2233娘_耶].png'>"
      },
      {
        "text":"bilibili2233-15",
        "icon":"<img src='https://cdn.jsdelivr.net/gh/2x-ercha/twikoo-magic@master/image/bilibili2233/[2233娘_郁闷].png'>"
      }
    ]
  },
  "滑稽":{
    "type":"image",
    "container":[
      {
        "text":"huaji-1",
        "icon":"<img src='https://cdn.jsdelivr.net/gh/2x-ercha/twikoo-magic@master/image/huaji/huaji(1).gif'>"
      },
      {
        "text":"huaji-2",
        "icon":"<img src='https://cdn.jsdelivr.net/gh/2x-ercha/twikoo-magic@master/image/huaji/huaji(1).jpg'>"
      },
      {
        "text":"huaji-3",
        "icon":"<img src='https://cdn.jsdelivr.net/gh/2x-ercha/twikoo-magic@master/image/huaji/huaji(1).png'>"
      },
      {
        "text":"huaji-4",
        "icon":"<img src='https://cdn.jsdelivr.net/gh/2x-ercha/twikoo-magic@master/image/huaji/huaji(10).gif'>"
      },
      {
        "text":"huaji-5",
        "icon":"<img src='https://cdn.jsdelivr.net/gh/2x-ercha/twikoo-magic@master/image/huaji/huaji(10).jpg'>"
      },
      {
        "text":"huaji-6",
        "icon":"<img src='https://cdn.jsdelivr.net/gh/2x-ercha/twikoo-magic@master/image/huaji/huaji(11).gif'>"
      },
      {
        "text":"huaji-7",
        "icon":"<img src='https://cdn.jsdelivr.net/gh/2x-ercha/twikoo-magic@master/image/huaji/huaji(11).jpg'>"
      },
      {
        "text":"huaji-8",
        "icon":"<img src='https://cdn.jsdelivr.net/gh/2x-ercha/twikoo-magic@master/image/huaji/huaji(12).gif'>"
      },
      {
        "text":"huaji-9",
        "icon":"<img src='https://cdn.jsdelivr.net/gh/2x-ercha/twikoo-magic@master/image/huaji/huaji(12).jpg'>"
      },
      {
        "text":"huaji-10",
        "icon":"<img src='https://cdn.jsdelivr.net/gh/2x-ercha/twikoo-magic@master/image/huaji/huaji(13).gif'>"
      },
      {
        "text":"huaji-11",
        "icon":"<img src='https://cdn.jsdelivr.net/gh/2x-ercha/twikoo-magic@master/image/huaji/huaji(13).jpg'>"
      },
      {
        "text":"huaji-12",
        "icon":"<img src='https://cdn.jsdelivr.net/gh/2x-ercha/twikoo-magic@master/image/huaji/huaji(14).gif'>"
      },
      {
        "text":"huaji-13",
        "icon":"<img src='https://cdn.jsdelivr.net/gh/2x-ercha/twikoo-magic@master/image/huaji/huaji(14).jpg'>"
      },
      {
        "text":"huaji-14",
        "icon":"<img src='https://cdn.jsdelivr.net/gh/2x-ercha/twikoo-magic@master/image/huaji/huaji(15).gif'>"
      },
      {
        "text":"huaji-15",
        "icon":"<img src='https://cdn.jsdelivr.net/gh/2x-ercha/twikoo-magic@master/image/huaji/huaji(15).jpg'>"
      },
      {
        "text":"huaji-16",
        "icon":"<img src='https://cdn.jsdelivr.net/gh/2x-ercha/twikoo-magic@master/image/huaji/huaji(16).gif'>"
      },
      {
        "text":"huaji-17",
        "icon":"<img src='https://cdn.jsdelivr.net/gh/2x-ercha/twikoo-magic@master/image/huaji/huaji(16).jpg'>"
      },
      {
        "text":"huaji-18",
        "icon":"<img src='https://cdn.jsdelivr.net/gh/2x-ercha/twikoo-magic@master/image/huaji/huaji(17).gif'>"
      },
      {
        "text":"huaji-19",
        "icon":"<img src='https://cdn.jsdelivr.net/gh/2x-ercha/twikoo-magic@master/image/huaji/huaji(17).jpg'>"
      },
      {
        "text":"huaji-20",
        "icon":"<img src='https://cdn.jsdelivr.net/gh/2x-ercha/twikoo-magic@master/image/huaji/huaji(18).gif'>"
      },
      {
        "text":"huaji-21",
        "icon":"<img src='https://cdn.jsdelivr.net/gh/2x-ercha/twikoo-magic@master/image/huaji/huaji(18).jpg'>"
      },
      {
        "text":"huaji-22",
        "icon":"<img src='https://cdn.jsdelivr.net/gh/2x-ercha/twikoo-magic@master/image/huaji/huaji(19).gif'>"
      },
      {
        "text":"huaji-23",
        "icon":"<img src='https://cdn.jsdelivr.net/gh/2x-ercha/twikoo-magic@master/image/huaji/huaji(19).jpg'>"
      },
      {
        "text":"huaji-24",
        "icon":"<img src='https://cdn.jsdelivr.net/gh/2x-ercha/twikoo-magic@master/image/huaji/huaji(2).gif'>"
      },
      {
        "text":"huaji-25",
        "icon":"<img src='https://cdn.jsdelivr.net/gh/2x-ercha/twikoo-magic@master/image/huaji/huaji(2).jpg'>"
      },
      {
        "text":"huaji-26",
        "icon":"<img src='https://cdn.jsdelivr.net/gh/2x-ercha/twikoo-magic@master/image/huaji/huaji(2).png'>"
      },
      {
        "text":"huaji-27",
        "icon":"<img src='https://cdn.jsdelivr.net/gh/2x-ercha/twikoo-magic@master/image/huaji/huaji(20).gif'>"
      },
      {
        "text":"huaji-28",
        "icon":"<img src='https://cdn.jsdelivr.net/gh/2x-ercha/twikoo-magic@master/image/huaji/huaji(20).jpg'>"
      },
      {
        "text":"huaji-29",
        "icon":"<img src='https://cdn.jsdelivr.net/gh/2x-ercha/twikoo-magic@master/image/huaji/huaji(21).gif'>"
      },
      {
        "text":"huaji-30",
        "icon":"<img src='https://cdn.jsdelivr.net/gh/2x-ercha/twikoo-magic@master/image/huaji/huaji(21).jpg'>"
      },
      {
        "text":"huaji-31",
        "icon":"<img src='https://cdn.jsdelivr.net/gh/2x-ercha/twikoo-magic@master/image/huaji/huaji(22).gif'>"
      },
      {
        "text":"huaji-32",
        "icon":"<img src='https://cdn.jsdelivr.net/gh/2x-ercha/twikoo-magic@master/image/huaji/huaji(22).jpg'>"
      },
      {
        "text":"huaji-33",
        "icon":"<img src='https://cdn.jsdelivr.net/gh/2x-ercha/twikoo-magic@master/image/huaji/huaji(23).gif'>"
      },
      {
        "text":"huaji-34",
        "icon":"<img src='https://cdn.jsdelivr.net/gh/2x-ercha/twikoo-magic@master/image/huaji/huaji(23).jpg'>"
      },
      {
        "text":"huaji-35",
        "icon":"<img src='https://cdn.jsdelivr.net/gh/2x-ercha/twikoo-magic@master/image/huaji/huaji(24).gif'>"
      },
      {
        "text":"huaji-36",
        "icon":"<img src='https://cdn.jsdelivr.net/gh/2x-ercha/twikoo-magic@master/image/huaji/huaji(24).jpg'>"
      },
      {
        "text":"huaji-37",
        "icon":"<img src='https://cdn.jsdelivr.net/gh/2x-ercha/twikoo-magic@master/image/huaji/huaji(25).gif'>"
      },
      {
        "text":"huaji-38",
        "icon":"<img src='https://cdn.jsdelivr.net/gh/2x-ercha/twikoo-magic@master/image/huaji/huaji(25).jpg'>"
      },
      {
        "text":"huaji-39",
        "icon":"<img src='https://cdn.jsdelivr.net/gh/2x-ercha/twikoo-magic@master/image/huaji/huaji(26).gif'>"
      },
      {
        "text":"huaji-40",
        "icon":"<img src='https://cdn.jsdelivr.net/gh/2x-ercha/twikoo-magic@master/image/huaji/huaji(26).jpg'>"
      },
      {
        "text":"huaji-41",
        "icon":"<img src='https://cdn.jsdelivr.net/gh/2x-ercha/twikoo-magic@master/image/huaji/huaji(27).gif'>"
      },
      {
        "text":"huaji-42",
        "icon":"<img src='https://cdn.jsdelivr.net/gh/2x-ercha/twikoo-magic@master/image/huaji/huaji(27).jpg'>"
      },
      {
        "text":"huaji-43",
        "icon":"<img src='https://cdn.jsdelivr.net/gh/2x-ercha/twikoo-magic@master/image/huaji/huaji(28).gif'>"
      },
      {
        "text":"huaji-44",
        "icon":"<img src='https://cdn.jsdelivr.net/gh/2x-ercha/twikoo-magic@master/image/huaji/huaji(28).jpg'>"
      },
      {
        "text":"huaji-45",
        "icon":"<img src='https://cdn.jsdelivr.net/gh/2x-ercha/twikoo-magic@master/image/huaji/huaji(29).gif'>"
      },
      {
        "text":"huaji-46",
        "icon":"<img src='https://cdn.jsdelivr.net/gh/2x-ercha/twikoo-magic@master/image/huaji/huaji(29).jpg'>"
      },
      {
        "text":"huaji-47",
        "icon":"<img src='https://cdn.jsdelivr.net/gh/2x-ercha/twikoo-magic@master/image/huaji/huaji(3).gif'>"
      },
      {
        "text":"huaji-48",
        "icon":"<img src='https://cdn.jsdelivr.net/gh/2x-ercha/twikoo-magic@master/image/huaji/huaji(3).jpg'>"
      },
      {
        "text":"huaji-49",
        "icon":"<img src='https://cdn.jsdelivr.net/gh/2x-ercha/twikoo-magic@master/image/huaji/huaji(3).png'>"
      },
      {
        "text":"huaji-50",
        "icon":"<img src='https://cdn.jsdelivr.net/gh/2x-ercha/twikoo-magic@master/image/huaji/huaji(30).gif'>"
      },
      {
        "text":"huaji-51",
        "icon":"<img src='https://cdn.jsdelivr.net/gh/2x-ercha/twikoo-magic@master/image/huaji/huaji(30).jpg'>"
      },
      {
        "text":"huaji-52",
        "icon":"<img src='https://cdn.jsdelivr.net/gh/2x-ercha/twikoo-magic@master/image/huaji/huaji(31).gif'>"
      },
      {
        "text":"huaji-53",
        "icon":"<img src='https://cdn.jsdelivr.net/gh/2x-ercha/twikoo-magic@master/image/huaji/huaji(31).jpg'>"
      },
      {
        "text":"huaji-54",
        "icon":"<img src='https://cdn.jsdelivr.net/gh/2x-ercha/twikoo-magic@master/image/huaji/huaji(32).gif'>"
      },
      {
        "text":"huaji-55",
        "icon":"<img src='https://cdn.jsdelivr.net/gh/2x-ercha/twikoo-magic@master/image/huaji/huaji(32).jpg'>"
      },
      {
        "text":"huaji-56",
        "icon":"<img src='https://cdn.jsdelivr.net/gh/2x-ercha/twikoo-magic@master/image/huaji/huaji(33).gif'>"
      },
      {
        "text":"huaji-57",
        "icon":"<img src='https://cdn.jsdelivr.net/gh/2x-ercha/twikoo-magic@master/image/huaji/huaji(33).jpg'>"
      },
      {
        "text":"huaji-58",
        "icon":"<img src='https://cdn.jsdelivr.net/gh/2x-ercha/twikoo-magic@master/image/huaji/huaji(34).gif'>"
      },
      {
        "text":"huaji-59",
        "icon":"<img src='https://cdn.jsdelivr.net/gh/2x-ercha/twikoo-magic@master/image/huaji/huaji(34).jpg'>"
      },
      {
        "text":"huaji-60",
        "icon":"<img src='https://cdn.jsdelivr.net/gh/2x-ercha/twikoo-magic@master/image/huaji/huaji(35).gif'>"
      },
      {
        "text":"huaji-61",
        "icon":"<img src='https://cdn.jsdelivr.net/gh/2x-ercha/twikoo-magic@master/image/huaji/huaji(35).jpg'>"
      },
      {
        "text":"huaji-62",
        "icon":"<img src='https://cdn.jsdelivr.net/gh/2x-ercha/twikoo-magic@master/image/huaji/huaji(36).gif'>"
      },
      {
        "text":"huaji-63",
        "icon":"<img src='https://cdn.jsdelivr.net/gh/2x-ercha/twikoo-magic@master/image/huaji/huaji(36).jpg'>"
      },
      {
        "text":"huaji-64",
        "icon":"<img src='https://cdn.jsdelivr.net/gh/2x-ercha/twikoo-magic@master/image/huaji/huaji(37).gif'>"
      },
      {
        "text":"huaji-65",
        "icon":"<img src='https://cdn.jsdelivr.net/gh/2x-ercha/twikoo-magic@master/image/huaji/huaji(37).jpg'>"
      },
      {
        "text":"huaji-66",
        "icon":"<img src='https://cdn.jsdelivr.net/gh/2x-ercha/twikoo-magic@master/image/huaji/huaji(38).gif'>"
      },
      {
        "text":"huaji-67",
        "icon":"<img src='https://cdn.jsdelivr.net/gh/2x-ercha/twikoo-magic@master/image/huaji/huaji(38).jpg'>"
      },
      {
        "text":"huaji-68",
        "icon":"<img src='https://cdn.jsdelivr.net/gh/2x-ercha/twikoo-magic@master/image/huaji/huaji(39).gif'>"
      },
      {
        "text":"huaji-69",
        "icon":"<img src='https://cdn.jsdelivr.net/gh/2x-ercha/twikoo-magic@master/image/huaji/huaji(39).jpg'>"
      },
      {
        "text":"huaji-70",
        "icon":"<img src='https://cdn.jsdelivr.net/gh/2x-ercha/twikoo-magic@master/image/huaji/huaji(4).gif'>"
      },
      {
        "text":"huaji-71",
        "icon":"<img src='https://cdn.jsdelivr.net/gh/2x-ercha/twikoo-magic@master/image/huaji/huaji(4).jpg'>"
      },
      {
        "text":"huaji-72",
        "icon":"<img src='https://cdn.jsdelivr.net/gh/2x-ercha/twikoo-magic@master/image/huaji/huaji(4).png'>"
      },
      {
        "text":"huaji-73",
        "icon":"<img src='https://cdn.jsdelivr.net/gh/2x-ercha/twikoo-magic@master/image/huaji/huaji(40).gif'>"
      },
      {
        "text":"huaji-74",
        "icon":"<img src='https://cdn.jsdelivr.net/gh/2x-ercha/twikoo-magic@master/image/huaji/huaji(40).jpg'>"
      },
      {
        "text":"huaji-75",
        "icon":"<img src='https://cdn.jsdelivr.net/gh/2x-ercha/twikoo-magic@master/image/huaji/huaji(41).gif'>"
      },
      {
        "text":"huaji-76",
        "icon":"<img src='https://cdn.jsdelivr.net/gh/2x-ercha/twikoo-magic@master/image/huaji/huaji(41).jpg'>"
      },
      {
        "text":"huaji-77",
        "icon":"<img src='https://cdn.jsdelivr.net/gh/2x-ercha/twikoo-magic@master/image/huaji/huaji(42).gif'>"
      },
      {
        "text":"huaji-78",
        "icon":"<img src='https://cdn.jsdelivr.net/gh/2x-ercha/twikoo-magic@master/image/huaji/huaji(42).jpg'>"
      },
      {
        "text":"huaji-79",
        "icon":"<img src='https://cdn.jsdelivr.net/gh/2x-ercha/twikoo-magic@master/image/huaji/huaji(43).gif'>"
      },
      {
        "text":"huaji-80",
        "icon":"<img src='https://cdn.jsdelivr.net/gh/2x-ercha/twikoo-magic@master/image/huaji/huaji(43).jpg'>"
      },
      {
        "text":"huaji-81",
        "icon":"<img src='https://cdn.jsdelivr.net/gh/2x-ercha/twikoo-magic@master/image/huaji/huaji(44).gif'>"
      },
      {
        "text":"huaji-82",
        "icon":"<img src='https://cdn.jsdelivr.net/gh/2x-ercha/twikoo-magic@master/image/huaji/huaji(44).jpg'>"
      },
      {
        "text":"huaji-83",
        "icon":"<img src='https://cdn.jsdelivr.net/gh/2x-ercha/twikoo-magic@master/image/huaji/huaji(45).gif'>"
      },
      {
        "text":"huaji-84",
        "icon":"<img src='https://cdn.jsdelivr.net/gh/2x-ercha/twikoo-magic@master/image/huaji/huaji(45).jpg'>"
      },
      {
        "text":"huaji-85",
        "icon":"<img src='https://cdn.jsdelivr.net/gh/2x-ercha/twikoo-magic@master/image/huaji/huaji(46).jpg'>"
      },
      {
        "text":"huaji-86",
        "icon":"<img src='https://cdn.jsdelivr.net/gh/2x-ercha/twikoo-magic@master/image/huaji/huaji(47).jpg'>"
      },
      {
        "text":"huaji-87",
        "icon":"<img src='https://cdn.jsdelivr.net/gh/2x-ercha/twikoo-magic@master/image/huaji/huaji(48).jpg'>"
      },
      {
        "text":"huaji-88",
        "icon":"<img src='https://cdn.jsdelivr.net/gh/2x-ercha/twikoo-magic@master/image/huaji/huaji(49).jpg'>"
      },
      {
        "text":"huaji-89",
        "icon":"<img src='https://cdn.jsdelivr.net/gh/2x-ercha/twikoo-magic@master/image/huaji/huaji(5).gif'>"
      },
      {
        "text":"huaji-90",
        "icon":"<img src='https://cdn.jsdelivr.net/gh/2x-ercha/twikoo-magic@master/image/huaji/huaji(5).jpg'>"
      },
      {
        "text":"huaji-91",
        "icon":"<img src='https://cdn.jsdelivr.net/gh/2x-ercha/twikoo-magic@master/image/huaji/huaji(5).png'>"
      },
      {
        "text":"huaji-92",
        "icon":"<img src='https://cdn.jsdelivr.net/gh/2x-ercha/twikoo-magic@master/image/huaji/huaji(6).gif'>"
      },
      {
        "text":"huaji-93",
        "icon":"<img src='https://cdn.jsdelivr.net/gh/2x-ercha/twikoo-magic@master/image/huaji/huaji(6).jpg'>"
      },
      {
        "text":"huaji-94",
        "icon":"<img src='https://cdn.jsdelivr.net/gh/2x-ercha/twikoo-magic@master/image/huaji/huaji(6).png'>"
      },
      {
        "text":"huaji-95",
        "icon":"<img src='https://cdn.jsdelivr.net/gh/2x-ercha/twikoo-magic@master/image/huaji/huaji(7).gif'>"
      },
      {
        "text":"huaji-96",
        "icon":"<img src='https://cdn.jsdelivr.net/gh/2x-ercha/twikoo-magic@master/image/huaji/huaji(7).jpg'>"
      },
      {
        "text":"huaji-97",
        "icon":"<img src='https://cdn.jsdelivr.net/gh/2x-ercha/twikoo-magic@master/image/huaji/huaji(8).gif'>"
      },
      {
        "text":"huaji-98",
        "icon":"<img src='https://cdn.jsdelivr.net/gh/2x-ercha/twikoo-magic@master/image/huaji/huaji(8).jpg'>"
      },
      {
        "text":"huaji-99",
        "icon":"<img src='https://cdn.jsdelivr.net/gh/2x-ercha/twikoo-magic@master/image/huaji/huaji(9).gif'>"
      },
      {
        "text":"huaji-100",
        "icon":"<img src='https://cdn.jsdelivr.net/gh/2x-ercha/twikoo-magic@master/image/huaji/huaji(9).jpg'>"
      }
    ]
  }
}