{
"HONKAI3-Star1": "HONKAI3-Star/1.gif",
"HONKAI3-Star2": "HONKAI3-Star/10.gif",
"HONKAI3-Star3": "HONKAI3-Star/11.gif",
"HONKAI3-Star4": "HONKAI3-Star/12.gif",
"HONKAI3-Star5": "HONKAI3-Star/13.gif",
"HONKAI3-Star6": "HONKAI3-Star/14.gif",
"HONKAI3-Star7": "HONKAI3-Star/15.gif",
"HONKAI3-Star8": "HONKAI3-Star/16.gif",
"HONKAI3-Star9": "HONKAI3-Star/2.gif",
"HONKAI3-Star10": "HONKAI3-Star/3.gif",
"HONKAI3-Star11": "HONKAI3-Star/4.gif",
"HONKAI3-Star12": "HONKAI3-Star/5.gif",
"HONKAI3-Star13": "HONKAI3-Star/6.gif",
"HONKAI3-Star14": "HONKAI3-Star/7.gif",
"HONKAI3-Star15": "HONKAI3-Star/8.gif",
"HONKAI3-Star16": "HONKAI3-Star/9.gif"
}