{
"lengtu1": "lengtu/01.gif",
"lengtu2": "lengtu/02.gif",
"lengtu3": "lengtu/03.gif",
"lengtu4": "lengtu/04.gif",
"lengtu5": "lengtu/05.gif",
"lengtu6": "lengtu/06.gif",
"lengtu7": "lengtu/07.gif",
"lengtu8": "lengtu/08.gif",
"lengtu9": "lengtu/09.gif",
"lengtu10": "lengtu/10.gif",
"lengtu11": "lengtu/11.gif",
"lengtu12": "lengtu/12.gif",
"lengtu13": "lengtu/13.gif",
"lengtu14": "lengtu/14.gif",
"lengtu15": "lengtu/15.gif",
"lengtu16": "lengtu/16.gif",
"lengtu17": "lengtu/17.gif",
"lengtu18": "lengtu/18.gif",
"lengtu19": "lengtu/19.gif",
"lengtu20": "lengtu/20.gif",
"lengtu21": "lengtu/21.gif",
"lengtu22": "lengtu/22.gif",
"lengtu23": "lengtu/23.gif",
"lengtu24": "lengtu/24.gif",
"lengtu25": "lengtu/25.gif",
"lengtu26": "lengtu/26.gif",
"lengtu27": "lengtu/27.gif",
"lengtu28": "lengtu/28.gif",
"lengtu29": "lengtu/29.gif",
"lengtu30": "lengtu/30.gif",
"lengtu31": "lengtu/31.gif",
"lengtu32": "lengtu/32.gif",
"lengtu33": "lengtu/33.gif",
"lengtu34": "lengtu/34.gif",
"lengtu35": "lengtu/35.gif",
"lengtu36": "lengtu/36.gif",
"lengtu37": "lengtu/37.gif",
"lengtu38": "lengtu/38.gif",
"lengtu39": "lengtu/39.gif",
"lengtu40": "lengtu/40.gif",
"lengtu41": "lengtu/41.gif",
"lengtu42": "lengtu/42.gif",
"lengtu43": "lengtu/43.gif",
"lengtu44": "lengtu/44.gif",
"lengtu45": "lengtu/45.gif",
"lengtu46": "lengtu/46.gif",
"lengtu47": "lengtu/47.gif",
"lengtu48": "lengtu/48.gif"
}